{
  "name": "Not 1080p",
  "includeCustomFormatWhenRenaming": false,
  "specifications": [
    {
      "name": "2160p",
      "implementation": "ResolutionSpecification",
      "negate": false,
      "required": false,
      "fields": {
        "value": 2160
      }
    },
    {
      "name": "720p",
      "implementation": "ResolutionSpecification",
      "negate": false,
      "required": false,
      "fields": {
        "value": 720
      }
    },
    {
      "name": "576p",
      "implementation": "ResolutionSpecification",
      "negate": false,
      "required": false,
      "fields": {
        "value": 576
      }
    },
    {
      "name": "540p",
      "implementation": "ResolutionSpecification",
      "negate": false,
      "required": false,
      "fields": {
        "value": 540
      }
    },
    {
      "name": "480p",
      "implementation": "ResolutionSpecification",
      "negate": false,
      "required": false,
      "fields": {
        "value": 480
      }
    },
    {
      "name": "360p",
      "implementation": "ResolutionSpecification",
      "negate": false,
      "required": false,
      "fields": {
        "value": 360
      }
    }
  ]
}